seismic_bedload/__init__.py
seismic_bedload/abc_class.py
seismic_bedload/models.py
seismic_bedload/utils.py
seismic_bedload-0.1.1.dist-info/METADATA
seismic_bedload-0.1.1.dist-info/WHEEL
seismic_bedload-0.1.1.dist-info/top_level.txt
seismic_bedload-0.1.1.dist-info/RECORD
