Metadata-Version: 2.4
Name: seismic_bedload
Version: 0.1.1
Summary: Seismic based bedload transport models
Author-email: Loc Luong <loc.k.luong@gmail.com>
License-Expression: MIT
Requires-Python: >=3.5
Requires-Dist: numpy
Requires-Dist: scipy
Requires-Dist: matplotlib
